sigrid/__init__.py
sigrid/systems/__init__.py
sigrid/systems/client.py
sigrid/systems/exceptions.py
sigrid/systems/stream.py
sigrid/systems/types.py
sigrid/systems/tyr.py
sigrid_systems-1.1.3.dist-info/METADATA
sigrid_systems-1.1.3.dist-info/WHEEL
sigrid_systems-1.1.3.dist-info/top_level.txt
sigrid_systems-1.1.3.dist-info/RECORD
