Metadata-Version: 2.4
Name: sigrid-systems
Version: 1.1.3
Summary: Python client library for SIGRID legal analysis API
Author: sigrid-systems.com
License: MIT
Classifier: Programming Language :: Python :: 3
Classifier: License :: OSI Approved :: MIT License
Classifier: Operating System :: OS Independent
Requires-Python: >=3.8
Requires-Dist: httpx>=0.24.0
